element_coder/__init__.py
element_coder/api.py
element_coder/cli.py
element_coder/decode.py
element_coder/encode.py
element_coder/utils.py
element_coder/version.py
element_coder/data/coding_data.py
element_coder/data/raw/atomic.json
element_coder/data/raw/atomic_radius_calculated.json
element_coder/data/raw/boiling_point.json
element_coder/data/raw/brinell_hardness.json
element_coder/data/raw/bulk_modulus.json
element_coder/data/raw/cgcnn.json
element_coder/data/raw/coefficient_of_linear_thermal_expansion.json
element_coder/data/raw/critical_temperature.json
element_coder/data/raw/density_of_solid.json
element_coder/data/raw/electrical_resistivity.json
element_coder/data/raw/electron_affinity.json
element_coder/data/raw/elemnet.json
element_coder/data/raw/jarvis.json
element_coder/data/raw/jarvis_sc.json
element_coder/data/raw/magpie.json
element_coder/data/raw/magpie_sc.json
element_coder/data/raw/mat2vec.json
element_coder/data/raw/matscholar.json
element_coder/data/raw/megnet16.json
element_coder/data/raw/melting_point.json
element_coder/data/raw/mendeleev.json
element_coder/data/raw/mineral_hardness.json
element_coder/data/raw/mod_petti.json
element_coder/data/raw/molar_volume.json
element_coder/data/raw/oliynyk.json
element_coder/data/raw/oliynyk_sc.json
element_coder/data/raw/petti.json
element_coder/data/raw/poissons_ratio.json
element_coder/data/raw/reflectivity.json
element_coder/data/raw/refractive_index.json
element_coder/data/raw/superconduction_temperature.json
element_coder/data/raw/thermal_conductivity.json
element_coder/data/raw/van_der_waals_radius.json
element_coder/data/raw/velocity_of_sound.json
element_coder/data/raw/vickers_hardness.json
element_coder/data/raw/x.json
element_coder/data/raw/youngs_modulus.json
element_coder-0.0.8.dist-info/LICENSE
element_coder-0.0.8.dist-info/METADATA
element_coder-0.0.8.dist-info/WHEEL
element_coder-0.0.8.dist-info/entry_points.txt
element_coder-0.0.8.dist-info/top_level.txt
element_coder-0.0.8.dist-info/RECORD
