Metadata-Version: 2.1
Name: element-coder
Version: 0.0.8
Summary: Encode chemical elements numerically and decode numerical representations of elements.
Home-page: https://github.com/kjappelbaum/element-coder
Download-URL: https://github.com/kjappelbaum/element-coder/releases
Author: Kevin M. Jablonka
Author-email: mail@kjablonka.com
Maintainer: Kevin M. Jablonka
Maintainer-email: mail@kjablonka.com
License: MIT
Project-URL: Bug Tracker, https://github.com/kjappelbaum/element-coder/issues
Project-URL: Source Code, https://github.com/kjappelbaum/element-coder
Keywords: element,periodic-table,chemistry
Classifier: Development Status :: 1 - Planning
Classifier: Environment :: Console
Classifier: Intended Audience :: Developers
Classifier: License :: OSI Approved :: MIT License
Classifier: Operating System :: OS Independent
Classifier: Framework :: Pytest
Classifier: Framework :: tox
Classifier: Framework :: Sphinx
Classifier: Programming Language :: Python
Classifier: Programming Language :: Python :: 3.8
Classifier: Programming Language :: Python :: 3.9
Classifier: Programming Language :: Python :: 3.10
Classifier: Programming Language :: Python :: 3 :: Only
Requires-Python: >=3.7
License-File: LICENSE
Requires-Dist: pymatgen
Requires-Dist: loguru
Requires-Dist: click
Provides-Extra: docs
Requires-Dist: sphinx ; extra == 'docs'
Requires-Dist: sphinx-rtd-theme ; extra == 'docs'
Requires-Dist: sphinx-click ; extra == 'docs'
Requires-Dist: sphinx-autodoc-typehints ; extra == 'docs'
Requires-Dist: sphinx-automodapi ; extra == 'docs'
Provides-Extra: lint
Requires-Dist: isort ; extra == 'lint'
Requires-Dist: black ; extra == 'lint'
Requires-Dist: flake8 ; extra == 'lint'
Requires-Dist: pre-commit ; extra == 'lint'
Requires-Dist: bumpversion ; extra == 'lint'
Provides-Extra: tests
Requires-Dist: pytest ; extra == 'tests'
Requires-Dist: tox ; extra == 'tests'
Requires-Dist: coverage ; extra == 'tests'
